plus/__init__.py
plus/config.py
plus/data/__init__.py
plus/data/alphabets.py
plus/data/dataset.py
plus/data/fasta.py
plus/data/fluorescence.py
plus/data/homology.py
plus/data/localization.py
plus/data/pfam.py
plus/data/secstr.py
plus/data/solubility.py
plus/data/stability.py
plus/data/transmembrane.py
plus/model/__init__.py
plus/model/cnn.py
plus/model/mlp.py
plus/model/p_elmo.py
plus/model/plus_rnn.py
plus/model/plus_tfm.py
plus/model/transformer.py
plus/optim.py
plus/preprocess.py
plus/train.py
plus/utils.py
bio_embeddings_plus-0.1.1.dist-info/LICENSE
bio_embeddings_plus-0.1.1.dist-info/WHEEL
bio_embeddings_plus-0.1.1.dist-info/METADATA
bio_embeddings_plus-0.1.1.dist-info/RECORD
