Metadata-Version: 2.1
Name: bio-embeddings-plus
Version: 0.1.1
Summary: Protein sequence representations Learned Using Structural information (https://arxiv.org/abs/1912.05625)
Author: Seonwoo Min
Requires-Python: >=3.6.1
Classifier: Programming Language :: Python :: 3
Classifier: Programming Language :: Python :: 3.7
Classifier: Programming Language :: Python :: 3.8
Classifier: Programming Language :: Python :: 3.9
Requires-Dist: numpy (>=1.17.4,<2.0.0)
Requires-Dist: pandas (>=1.1.1,<2.0.0)
Requires-Dist: scipy (>=1.4.1,<2.0.0)
Requires-Dist: torch (>=1.3.1,<2.0.0)
Project-URL: homepage, http://ailab.snu.ac.kr/PLUS/
Project-URL: issues, https://github.com/mswzeus/PLUS/issues
Project-URL: repository, https://github.com/mswzeus/PLUS
